
{
  "_lang": "csharp",
  "_tocPath": "reference/toc.html",
  "_navPath": "toc.html",
  "_rel": "../",
  "_navRel": "../toc.html",
  "_tocRel": "toc.html",
  "_appTitle": "Entity Framework",
  "item": {
    "uid": "Microsoft.Data.Entity.ChangeTracking.Internal.KeyValue`1",
    "id": "KeyValue_T_",
    "parent": "Microsoft.Data.Entity.ChangeTracking.Internal",
    "children": [
      {
        "title": "Constructors",
        "id": "constructors",
        "children": [
          {
            "uid": "Microsoft.Data.Entity.ChangeTracking.Internal.KeyValue`1.#ctor(Microsoft.Data.Entity.Metadata.IKey,`0)",
            "id": "KeyValue_IKey__T_",
            "parent": "Microsoft.Data.Entity.ChangeTracking.Internal.KeyValue`1",
            "href": "Microsoft.Data.Entity.ChangeTracking.Internal.KeyValue`1.yml",
            "name": "KeyValue(IKey, T)",
            "fullName": "Microsoft.Data.Entity.ChangeTracking.Internal.KeyValue<T>.KeyValue(Microsoft.Data.Entity.Metadata.IKey, T)",
            "fullName.vb": "Microsoft.Data.Entity.ChangeTracking.Internal.KeyValue(Of T).KeyValue(Microsoft.Data.Entity.Metadata.IKey, T)",
            "type": "constructor",
            "source": {
              "remote": {
                "path": "src/EntityFramework.Core/ChangeTracking/Internal/KeyValue.cs",
                "branch": "dev",
                "repo": "https://github.com/chenkennt/EntityFramework.git"
              },
              "path": "src/EntityFramework.Core/ChangeTracking/Internal/KeyValue.cs",
              "startLine": 33,
              "endLine": 0,
              "isExternal": false
            },
            "assemblies": [
              "EntityFramework.Core"
            ],
            "namespace": "Microsoft.Data.Entity.ChangeTracking.Internal",
            "syntax": {
              "content": "public KeyValue(IKey key, T value)",
              "content.vb": "Public Sub New(key As IKey, value As T)",
              "parameters": [
                {
                  "id": "key",
                  "type": {
                    "uid": "Microsoft.Data.Entity.Metadata.IKey",
                    "parent": "Microsoft.Data.Entity.Metadata",
                    "isExternal": false,
                    "href": "Microsoft.Data.Entity.Metadata.IKey.yml",
                    "name": "IKey",
                    "fullName": "Microsoft.Data.Entity.Metadata.IKey",
                    "specName": "<xref href=\"Microsoft.Data.Entity.Metadata.IKey\" name=\"Microsoft.Data.Entity.Metadata.IKey\"/>",
                    "id": "IKey",
                    "level": 0
                  }
                },
                {
                  "id": "value",
                  "type": {
                    "uid": "{T}",
                    "isExternal": false,
                    "name": "T",
                    "fullName": "T",
                    "specName": "<xref href=\"{T}\" name=\"T\"/>",
                    "id": "T",
                    "level": 0
                  }
                }
              ]
            },
            "specName": "<xref href=\"Microsoft.Data.Entity.ChangeTracking.Internal.KeyValue`1.#ctor(Microsoft.Data.Entity.Metadata.IKey,`0)\" name=\"Microsoft.Data.Entity.ChangeTracking.Internal.KeyValue&lt;T&gt;.KeyValue(Microsoft.Data.Entity.Metadata.IKey, T)\"/>",
            "level": 0,
            "docurl": "",
            "sourceurl": "https://github.com/chenkennt/EntityFramework/blob/dev/src/EntityFramework.Core/ChangeTracking/Internal/KeyValue.cs/#L34"
          }
        ]
      },
      {
        "title": "Properties",
        "id": "properties",
        "children": [
          {
            "uid": "Microsoft.Data.Entity.ChangeTracking.Internal.KeyValue`1.IsInvalid",
            "id": "IsInvalid",
            "parent": "Microsoft.Data.Entity.ChangeTracking.Internal.KeyValue`1",
            "href": "Microsoft.Data.Entity.ChangeTracking.Internal.KeyValue`1.yml",
            "name": "IsInvalid",
            "fullName": "Microsoft.Data.Entity.ChangeTracking.Internal.KeyValue<T>.IsInvalid",
            "fullName.vb": "Microsoft.Data.Entity.ChangeTracking.Internal.KeyValue(Of T).IsInvalid",
            "type": "property",
            "source": {
              "remote": {
                "path": "src/EntityFramework.Core/ChangeTracking/Internal/KeyValue.cs",
                "branch": "dev",
                "repo": "https://github.com/chenkennt/EntityFramework.git"
              },
              "path": "src/EntityFramework.Core/ChangeTracking/Internal/KeyValue.cs",
              "startLine": 39,
              "endLine": 0,
              "isExternal": false
            },
            "assemblies": [
              "EntityFramework.Core"
            ],
            "namespace": "Microsoft.Data.Entity.ChangeTracking.Internal",
            "syntax": {
                "content": "public bool IsInvalid { get; }",
                "content.vb": "Public ReadOnly Property IsInvalid As Boolean",
                "parameters": [],
                "return": {
                  "type": {
                    "uid": "System.Boolean",
                    "parent": "System",
                    "isExternal": true,
                    "name": "Boolean",
                    "fullName": "System.Boolean",
                    "specName": "<xref href=\"System.Boolean\" name=\"System.Boolean\"/>",
                    "id": "Boolean",
                    "level": 0
                  }
                }
            },
            "specName": "<xref href=\"Microsoft.Data.Entity.ChangeTracking.Internal.KeyValue`1.IsInvalid\" name=\"Microsoft.Data.Entity.ChangeTracking.Internal.KeyValue&lt;T&gt;.IsInvalid\"/>",
            "level": 0,
            "docurl": "",
            "sourceurl": "https://github.com/chenkennt/EntityFramework/blob/dev/src/EntityFramework.Core/ChangeTracking/Internal/KeyValue.cs/#L40"
          },
          {
            "uid": "Microsoft.Data.Entity.ChangeTracking.Internal.KeyValue`1.Key",
            "id": "Key",
            "parent": "Microsoft.Data.Entity.ChangeTracking.Internal.KeyValue`1",
            "href": "Microsoft.Data.Entity.ChangeTracking.Internal.KeyValue`1.yml",
            "name": "Key",
            "fullName": "Microsoft.Data.Entity.ChangeTracking.Internal.KeyValue<T>.Key",
            "fullName.vb": "Microsoft.Data.Entity.ChangeTracking.Internal.KeyValue(Of T).Key",
            "type": "property",
            "source": {
              "remote": {
                "path": "src/EntityFramework.Core/ChangeTracking/Internal/KeyValue.cs",
                "branch": "dev",
                "repo": "https://github.com/chenkennt/EntityFramework.git"
              },
              "path": "src/EntityFramework.Core/ChangeTracking/Internal/KeyValue.cs",
              "startLine": 41,
              "endLine": 0,
              "isExternal": false
            },
            "assemblies": [
              "EntityFramework.Core"
            ],
            "namespace": "Microsoft.Data.Entity.ChangeTracking.Internal",
            "syntax": {
                "content": "public IKey Key { get; }",
                "content.vb": "Public ReadOnly Property Key As IKey",
                "parameters": [],
                "return": {
                  "type": {
                    "uid": "Microsoft.Data.Entity.Metadata.IKey",
                    "parent": "Microsoft.Data.Entity.Metadata",
                    "isExternal": false,
                    "href": "Microsoft.Data.Entity.Metadata.IKey.yml",
                    "name": "IKey",
                    "fullName": "Microsoft.Data.Entity.Metadata.IKey",
                    "specName": "<xref href=\"Microsoft.Data.Entity.Metadata.IKey\" name=\"Microsoft.Data.Entity.Metadata.IKey\"/>",
                    "id": "IKey",
                    "level": 0
                  }
                }
            },
            "specName": "<xref href=\"Microsoft.Data.Entity.ChangeTracking.Internal.KeyValue`1.Key\" name=\"Microsoft.Data.Entity.ChangeTracking.Internal.KeyValue&lt;T&gt;.Key\"/>",
            "level": 0,
            "docurl": "",
            "sourceurl": "https://github.com/chenkennt/EntityFramework/blob/dev/src/EntityFramework.Core/ChangeTracking/Internal/KeyValue.cs/#L42"
          },
          {
            "uid": "Microsoft.Data.Entity.ChangeTracking.Internal.KeyValue`1.Value",
            "id": "Value",
            "parent": "Microsoft.Data.Entity.ChangeTracking.Internal.KeyValue`1",
            "href": "Microsoft.Data.Entity.ChangeTracking.Internal.KeyValue`1.yml",
            "name": "Value",
            "fullName": "Microsoft.Data.Entity.ChangeTracking.Internal.KeyValue<T>.Value",
            "fullName.vb": "Microsoft.Data.Entity.ChangeTracking.Internal.KeyValue(Of T).Value",
            "type": "property",
            "source": {
              "remote": {
                "path": "src/EntityFramework.Core/ChangeTracking/Internal/KeyValue.cs",
                "branch": "dev",
                "repo": "https://github.com/chenkennt/EntityFramework.git"
              },
              "path": "src/EntityFramework.Core/ChangeTracking/Internal/KeyValue.cs",
              "startLine": 43,
              "endLine": 0,
              "isExternal": false
            },
            "assemblies": [
              "EntityFramework.Core"
            ],
            "namespace": "Microsoft.Data.Entity.ChangeTracking.Internal",
            "syntax": {
                "content": "public object Value { get; }",
                "content.vb": "Public ReadOnly Property Value As Object",
                "parameters": [],
                "return": {
                  "type": {
                    "uid": "System.Object",
                    "parent": "System",
                    "isExternal": true,
                    "name": "Object",
                    "fullName": "System.Object",
                    "specName": "<xref href=\"System.Object\" name=\"System.Object\"/>",
                    "id": "Object",
                    "level": 0
                  }
                }
            },
            "specName": "<xref href=\"Microsoft.Data.Entity.ChangeTracking.Internal.KeyValue`1.Value\" name=\"Microsoft.Data.Entity.ChangeTracking.Internal.KeyValue&lt;T&gt;.Value\"/>",
            "level": 0,
            "docurl": "",
            "sourceurl": "https://github.com/chenkennt/EntityFramework/blob/dev/src/EntityFramework.Core/ChangeTracking/Internal/KeyValue.cs/#L44"
          }
        ]
      },
      {
        "title": "Methods",
        "id": "methods",
        "children": [
          {
            "uid": "Microsoft.Data.Entity.ChangeTracking.Internal.KeyValue`1.Equals(System.Object)",
            "id": "Equals_Object_",
            "parent": "Microsoft.Data.Entity.ChangeTracking.Internal.KeyValue`1",
            "href": "Microsoft.Data.Entity.ChangeTracking.Internal.KeyValue`1.yml",
            "name": "Equals(Object)",
            "fullName": "Microsoft.Data.Entity.ChangeTracking.Internal.KeyValue<T>.Equals(System.Object)",
            "fullName.vb": "Microsoft.Data.Entity.ChangeTracking.Internal.KeyValue(Of T).Equals(System.Object)",
            "type": "method",
            "source": {
              "remote": {
                "path": "src/EntityFramework.Core/ChangeTracking/Internal/KeyValue.cs",
                "branch": "dev",
                "repo": "https://github.com/chenkennt/EntityFramework.git"
              },
              "path": "src/EntityFramework.Core/ChangeTracking/Internal/KeyValue.cs",
              "startLine": 45,
              "endLine": 0,
              "isExternal": false
            },
            "assemblies": [
              "EntityFramework.Core"
            ],
            "namespace": "Microsoft.Data.Entity.ChangeTracking.Internal",
            "syntax": {
              "content": "public override bool Equals(object obj)",
              "content.vb": "Public Overrides Function Equals(obj As Object) As Boolean",
              "parameters": [
                {
                  "id": "obj",
                  "type": {
                    "uid": "System.Object",
                    "parent": "System",
                    "isExternal": true,
                    "name": "Object",
                    "fullName": "System.Object",
                    "specName": "<xref href=\"System.Object\" name=\"System.Object\"/>",
                    "id": "Object",
                    "level": 0
                  }
                }
              ],
              "return": {
                "type": {
                  "uid": "System.Boolean",
                  "parent": "System",
                  "isExternal": true,
                  "name": "Boolean",
                  "fullName": "System.Boolean",
                  "specName": "<xref href=\"System.Boolean\" name=\"System.Boolean\"/>",
                  "id": "Boolean",
                  "level": 0
                }
              }
            },
            "overridden": "System.ValueType.Equals(System.Object)",
            "specName": "<xref href=\"Microsoft.Data.Entity.ChangeTracking.Internal.KeyValue`1.Equals(System.Object)\" name=\"Microsoft.Data.Entity.ChangeTracking.Internal.KeyValue&lt;T&gt;.Equals(System.Object)\"/>",
            "level": 0,
            "docurl": "",
            "sourceurl": "https://github.com/chenkennt/EntityFramework/blob/dev/src/EntityFramework.Core/ChangeTracking/Internal/KeyValue.cs/#L46"
          },
          {
            "uid": "Microsoft.Data.Entity.ChangeTracking.Internal.KeyValue`1.GetHashCode",
            "id": "GetHashCode__",
            "parent": "Microsoft.Data.Entity.ChangeTracking.Internal.KeyValue`1",
            "href": "Microsoft.Data.Entity.ChangeTracking.Internal.KeyValue`1.yml",
            "name": "GetHashCode()",
            "fullName": "Microsoft.Data.Entity.ChangeTracking.Internal.KeyValue<T>.GetHashCode()",
            "fullName.vb": "Microsoft.Data.Entity.ChangeTracking.Internal.KeyValue(Of T).GetHashCode()",
            "type": "method",
            "source": {
              "remote": {
                "path": "src/EntityFramework.Core/ChangeTracking/Internal/KeyValue.cs",
                "branch": "dev",
                "repo": "https://github.com/chenkennt/EntityFramework.git"
              },
              "path": "src/EntityFramework.Core/ChangeTracking/Internal/KeyValue.cs",
              "startLine": 54,
              "endLine": 0,
              "isExternal": false
            },
            "assemblies": [
              "EntityFramework.Core"
            ],
            "namespace": "Microsoft.Data.Entity.ChangeTracking.Internal",
            "syntax": {
              "content": "public override int GetHashCode()",
              "content.vb": "Public Overrides Function GetHashCode As Integer",
              "return": {
                "type": {
                  "uid": "System.Int32",
                  "parent": "System",
                  "isExternal": true,
                  "name": "Int32",
                  "fullName": "System.Int32",
                  "specName": "<xref href=\"System.Int32\" name=\"System.Int32\"/>",
                  "id": "Int32",
                  "level": 0
                }
              }
            },
            "overridden": "System.ValueType.GetHashCode",
            "specName": "<xref href=\"Microsoft.Data.Entity.ChangeTracking.Internal.KeyValue`1.GetHashCode\" name=\"Microsoft.Data.Entity.ChangeTracking.Internal.KeyValue&lt;T&gt;.GetHashCode()\"/>",
            "level": 0,
            "docurl": "",
            "sourceurl": "https://github.com/chenkennt/EntityFramework/blob/dev/src/EntityFramework.Core/ChangeTracking/Internal/KeyValue.cs/#L55"
          }
        ]
      }
    ],
    "href": "Microsoft.Data.Entity.ChangeTracking.Internal.KeyValue`1.yml",
    "name": "KeyValue<T>",
    "name.vb": "KeyValue(Of T)",
    "fullName": "Microsoft.Data.Entity.ChangeTracking.Internal.KeyValue<T>",
    "fullName.vb": "Microsoft.Data.Entity.ChangeTracking.Internal.KeyValue(Of T)",
    "type": "Struct",
    "source": {
      "remote": {
        "path": "src/EntityFramework.Core/ChangeTracking/Internal/KeyValue.cs",
        "branch": "dev",
        "repo": "https://github.com/chenkennt/EntityFramework.git"
      },
      "path": "src/EntityFramework.Core/ChangeTracking/Internal/KeyValue.cs",
      "startLine": 13,
      "endLine": 0,
      "isExternal": false
    },
    "assemblies": [
      "EntityFramework.Core"
    ],
    "namespace": "Microsoft.Data.Entity.ChangeTracking.Internal",
    "syntax": {
      "content": "public struct KeyValue<T> : IKeyValue",
      "content.vb": "Public Structure KeyValue(Of T) Implements IKeyValue",
      "typeParameters": [
        {
          "id": "T"
        }
      ]
    },
    "implements": [
      "Microsoft.Data.Entity.Infrastructure.IKeyValue"
    ],
    "inheritedMembers": [
      "System.ValueType.ToString",
      "System.Object.Equals(System.Object,System.Object)",
      "System.Object.ReferenceEquals(System.Object,System.Object)",
      "System.Object.GetType"
    ],
    "specName": "<xref href=\"Microsoft.Data.Entity.ChangeTracking.Internal.KeyValue`1\" name=\"Microsoft.Data.Entity.ChangeTracking.Internal.KeyValue&lt;T&gt;\"/>",
    "level": 0,
    "docurl": "",
    "sourceurl": "https://github.com/chenkennt/EntityFramework/blob/dev/src/EntityFramework.Core/ChangeTracking/Internal/KeyValue.cs/#L14"
  },
  "isClass": true,
  "_allowToc": true
}
