
{
  "_lang": "csharp",
  "_tocPath": "reference/toc.html",
  "_navPath": "toc.html",
  "_rel": "../",
  "_navRel": "../toc.html",
  "_tocRel": "toc.html",
  "_appTitle": "Entity Framework",
  "item": {
    "uid": "Microsoft.Data.Entity.Design.DatabaseOperations",
    "id": "DatabaseOperations",
    "parent": "Microsoft.Data.Entity.Design",
    "children": [
      {
        "title": "Constructors",
        "id": "constructors",
        "children": [
          {
            "uid": "Microsoft.Data.Entity.Design.DatabaseOperations.#ctor(Microsoft.Extensions.Logging.ILoggerProvider,System.String,System.String,System.String,System.String,System.String)",
            "id": "DatabaseOperations_ILoggerProvider__String__String__String__String__String_",
            "parent": "Microsoft.Data.Entity.Design.DatabaseOperations",
            "href": "Microsoft.Data.Entity.Design.DatabaseOperations.yml",
            "name": "DatabaseOperations(ILoggerProvider, String, String, String, String, String)",
            "fullName": "Microsoft.Data.Entity.Design.DatabaseOperations.DatabaseOperations(Microsoft.Extensions.Logging.ILoggerProvider, System.String, System.String, System.String, System.String, System.String)",
            "type": "constructor",
            "source": {
              "remote": {
                "path": "src/EntityFramework.Commands/Design/DatabaseOperations.cs",
                "branch": "dev",
                "repo": "https://github.com/chenkennt/EntityFramework.git"
              },
              "path": "src/EntityFramework.Commands/Design/DatabaseOperations.cs",
              "startLine": 24,
              "endLine": 0,
              "isExternal": false
            },
            "assemblies": [
              "EntityFramework.Commands"
            ],
            "namespace": "Microsoft.Data.Entity.Design",
            "syntax": {
              "content": "public DatabaseOperations(ILoggerProvider loggerProvider, string assemblyName, string startupAssemblyName, string environment, string projectDir, string rootNamespace)",
              "content.vb": "Public Sub New(loggerProvider As ILoggerProvider, assemblyName As String, startupAssemblyName As String, environment As String, projectDir As String, rootNamespace As String)",
              "parameters": [
                {
                  "id": "loggerProvider",
                  "type": {
                    "uid": "Microsoft.Extensions.Logging.ILoggerProvider",
                    "parent": "Microsoft.Extensions.Logging",
                    "isExternal": true,
                    "name": "ILoggerProvider",
                    "fullName": "Microsoft.Extensions.Logging.ILoggerProvider",
                    "specName": "<xref href=\"Microsoft.Extensions.Logging.ILoggerProvider\" name=\"Microsoft.Extensions.Logging.ILoggerProvider\"/>",
                    "id": "ILoggerProvider",
                    "level": 0
                  }
                },
                {
                  "id": "assemblyName",
                  "type": {
                    "uid": "System.String",
                    "parent": "System",
                    "isExternal": true,
                    "name": "String",
                    "fullName": "System.String",
                    "specName": "<xref href=\"System.String\" name=\"System.String\"/>",
                    "id": "String",
                    "level": 0
                  }
                },
                {
                  "id": "startupAssemblyName",
                  "type": {
                    "uid": "System.String",
                    "parent": "System",
                    "isExternal": true,
                    "name": "String",
                    "fullName": "System.String",
                    "specName": "<xref href=\"System.String\" name=\"System.String\"/>",
                    "id": "String",
                    "level": 0
                  }
                },
                {
                  "id": "environment",
                  "type": {
                    "uid": "System.String",
                    "parent": "System",
                    "isExternal": true,
                    "name": "String",
                    "fullName": "System.String",
                    "specName": "<xref href=\"System.String\" name=\"System.String\"/>",
                    "id": "String",
                    "level": 0
                  }
                },
                {
                  "id": "projectDir",
                  "type": {
                    "uid": "System.String",
                    "parent": "System",
                    "isExternal": true,
                    "name": "String",
                    "fullName": "System.String",
                    "specName": "<xref href=\"System.String\" name=\"System.String\"/>",
                    "id": "String",
                    "level": 0
                  }
                },
                {
                  "id": "rootNamespace",
                  "type": {
                    "uid": "System.String",
                    "parent": "System",
                    "isExternal": true,
                    "name": "String",
                    "fullName": "System.String",
                    "specName": "<xref href=\"System.String\" name=\"System.String\"/>",
                    "id": "String",
                    "level": 0
                  }
                }
              ]
            },
            "specName": "<xref href=\"Microsoft.Data.Entity.Design.DatabaseOperations.#ctor(Microsoft.Extensions.Logging.ILoggerProvider,System.String,System.String,System.String,System.String,System.String)\" name=\"Microsoft.Data.Entity.Design.DatabaseOperations.DatabaseOperations(Microsoft.Extensions.Logging.ILoggerProvider, System.String, System.String, System.String, System.String, System.String)\"/>",
            "level": 0,
            "docurl": "",
            "sourceurl": "https://github.com/chenkennt/EntityFramework/blob/dev/src/EntityFramework.Commands/Design/DatabaseOperations.cs/#L25"
          }
        ]
      },
      {
        "title": "Methods",
        "id": "methods",
        "children": [
          {
            "uid": "Microsoft.Data.Entity.Design.DatabaseOperations.ReverseEngineerAsync(System.String,System.String,System.String,System.String,System.Collections.Generic.List{System.String},System.Collections.Generic.List{System.String},System.Boolean,System.Threading.CancellationToken)",
            "id": "ReverseEngineerAsync_String__String__String__String__List_String___List_String___Boolean__CancellationToken_",
            "parent": "Microsoft.Data.Entity.Design.DatabaseOperations",
            "href": "Microsoft.Data.Entity.Design.DatabaseOperations.yml",
            "name": "ReverseEngineerAsync(String, String, String, String, List<String>, List<String>, Boolean, CancellationToken)",
            "name.vb": "ReverseEngineerAsync(String, String, String, String, List(Of String), List(Of String), Boolean, CancellationToken)",
            "fullName": "Microsoft.Data.Entity.Design.DatabaseOperations.ReverseEngineerAsync(System.String, System.String, System.String, System.String, System.Collections.Generic.List<System.String>, System.Collections.Generic.List<System.String>, System.Boolean, System.Threading.CancellationToken)",
            "fullName.vb": "Microsoft.Data.Entity.Design.DatabaseOperations.ReverseEngineerAsync(System.String, System.String, System.String, System.String, System.Collections.Generic.List(Of System.String), System.Collections.Generic.List(Of System.String), System.Boolean, System.Threading.CancellationToken)",
            "type": "method",
            "source": {
              "remote": {
                "path": "src/EntityFramework.Commands/Design/DatabaseOperations.cs",
                "branch": "dev",
                "repo": "https://github.com/chenkennt/EntityFramework.git"
              },
              "path": "src/EntityFramework.Commands/Design/DatabaseOperations.cs",
              "startLine": 46,
              "endLine": 0,
              "isExternal": false
            },
            "assemblies": [
              "EntityFramework.Commands"
            ],
            "namespace": "Microsoft.Data.Entity.Design",
            "syntax": {
              "content": "public virtual Task<ReverseEngineerFiles> ReverseEngineerAsync(string provider, string connectionString, string outputDir, string dbContextClassName, List<string> schemas, List<string> tables, bool useDataAnnotations, CancellationToken cancellationToken = null)",
              "content.vb": "Public Overridable Function ReverseEngineerAsync(provider As String, connectionString As String, outputDir As String, dbContextClassName As String, schemas As List(Of String), tables As List(Of String), useDataAnnotations As Boolean, cancellationToken As CancellationToken = Nothing) As Task(Of ReverseEngineerFiles)",
              "parameters": [
                {
                  "id": "provider",
                  "type": {
                    "uid": "System.String",
                    "parent": "System",
                    "isExternal": true,
                    "name": "String",
                    "fullName": "System.String",
                    "specName": "<xref href=\"System.String\" name=\"System.String\"/>",
                    "id": "String",
                    "level": 0
                  }
                },
                {
                  "id": "connectionString",
                  "type": {
                    "uid": "System.String",
                    "parent": "System",
                    "isExternal": true,
                    "name": "String",
                    "fullName": "System.String",
                    "specName": "<xref href=\"System.String\" name=\"System.String\"/>",
                    "id": "String",
                    "level": 0
                  }
                },
                {
                  "id": "outputDir",
                  "type": {
                    "uid": "System.String",
                    "parent": "System",
                    "isExternal": true,
                    "name": "String",
                    "fullName": "System.String",
                    "specName": "<xref href=\"System.String\" name=\"System.String\"/>",
                    "id": "String",
                    "level": 0
                  }
                },
                {
                  "id": "dbContextClassName",
                  "type": {
                    "uid": "System.String",
                    "parent": "System",
                    "isExternal": true,
                    "name": "String",
                    "fullName": "System.String",
                    "specName": "<xref href=\"System.String\" name=\"System.String\"/>",
                    "id": "String",
                    "level": 0
                  }
                },
                {
                  "id": "schemas",
                  "type": {
                    "uid": "System.Collections.Generic.List{System.String}",
                    "parent": "System.Collections.Generic",
                    "definition": "System.Collections.Generic.List`1",
                    "name": "List<String>",
                    "name.vb": "List(Of String)",
                    "fullName": "System.Collections.Generic.List<System.String>",
                    "fullName.vb": "System.Collections.Generic.List(Of System.String)",
                    "spec.csharp": [
                      {
                        "uid": "System.Collections.Generic.List`1",
                        "name": "List",
                        "fullName": "System.Collections.Generic.List",
                        "isExternal": true
                      },
                      {
                        "name": "<",
                        "fullName": "<",
                        "isExternal": false
                      },
                      {
                        "uid": "System.String",
                        "name": "String",
                        "fullName": "System.String",
                        "isExternal": true
                      },
                      {
                        "name": ">",
                        "fullName": ">",
                        "isExternal": false
                      }
                    ],
                    "spec.vb": [
                      {
                        "uid": "System.Collections.Generic.List`1",
                        "name": "List",
                        "fullName": "System.Collections.Generic.List",
                        "isExternal": true
                      },
                      {
                        "name": "(Of ",
                        "fullName": "(Of ",
                        "isExternal": false
                      },
                      {
                        "uid": "System.String",
                        "name": "String",
                        "fullName": "System.String",
                        "isExternal": true
                      },
                      {
                        "name": ")",
                        "fullName": ")",
                        "isExternal": false
                      }
                    ],
                    "specName": "<xref href=\"System.Collections.Generic.List`1\" name=\"System.Collections.Generic.List\"/>&lt;<xref href=\"System.String\" name=\"System.String\"/>&gt;",
                    "id": "List_String_",
                    "level": 0
                  }
                },
                {
                  "id": "tables",
                  "type": {
                    "uid": "System.Collections.Generic.List{System.String}",
                    "parent": "System.Collections.Generic",
                    "definition": "System.Collections.Generic.List`1",
                    "name": "List<String>",
                    "name.vb": "List(Of String)",
                    "fullName": "System.Collections.Generic.List<System.String>",
                    "fullName.vb": "System.Collections.Generic.List(Of System.String)",
                    "spec.csharp": [
                      {
                        "uid": "System.Collections.Generic.List`1",
                        "name": "List",
                        "fullName": "System.Collections.Generic.List",
                        "isExternal": true
                      },
                      {
                        "name": "<",
                        "fullName": "<",
                        "isExternal": false
                      },
                      {
                        "uid": "System.String",
                        "name": "String",
                        "fullName": "System.String",
                        "isExternal": true
                      },
                      {
                        "name": ">",
                        "fullName": ">",
                        "isExternal": false
                      }
                    ],
                    "spec.vb": [
                      {
                        "uid": "System.Collections.Generic.List`1",
                        "name": "List",
                        "fullName": "System.Collections.Generic.List",
                        "isExternal": true
                      },
                      {
                        "name": "(Of ",
                        "fullName": "(Of ",
                        "isExternal": false
                      },
                      {
                        "uid": "System.String",
                        "name": "String",
                        "fullName": "System.String",
                        "isExternal": true
                      },
                      {
                        "name": ")",
                        "fullName": ")",
                        "isExternal": false
                      }
                    ],
                    "specName": "<xref href=\"System.Collections.Generic.List`1\" name=\"System.Collections.Generic.List\"/>&lt;<xref href=\"System.String\" name=\"System.String\"/>&gt;",
                    "id": "List_String_",
                    "level": 0
                  }
                },
                {
                  "id": "useDataAnnotations",
                  "type": {
                    "uid": "System.Boolean",
                    "parent": "System",
                    "isExternal": true,
                    "name": "Boolean",
                    "fullName": "System.Boolean",
                    "specName": "<xref href=\"System.Boolean\" name=\"System.Boolean\"/>",
                    "id": "Boolean",
                    "level": 0
                  }
                },
                {
                  "id": "cancellationToken",
                  "type": {
                    "uid": "System.Threading.CancellationToken",
                    "parent": "System.Threading",
                    "isExternal": true,
                    "name": "CancellationToken",
                    "fullName": "System.Threading.CancellationToken",
                    "specName": "<xref href=\"System.Threading.CancellationToken\" name=\"System.Threading.CancellationToken\"/>",
                    "id": "CancellationToken",
                    "level": 0
                  }
                }
              ],
              "return": {
                "type": {
                  "uid": "System.Threading.Tasks.Task{Microsoft.Data.Entity.Scaffolding.Internal.ReverseEngineerFiles}",
                  "parent": "System.Threading.Tasks",
                  "definition": "System.Threading.Tasks.Task`1",
                  "href": "Microsoft.Data.Entity.Scaffolding.Internal.ReverseEngineerFiles.yml",
                  "name": "Task<ReverseEngineerFiles>",
                  "name.vb": "Task(Of ReverseEngineerFiles)",
                  "fullName": "System.Threading.Tasks.Task<Microsoft.Data.Entity.Scaffolding.Internal.ReverseEngineerFiles>",
                  "fullName.vb": "System.Threading.Tasks.Task(Of Microsoft.Data.Entity.Scaffolding.Internal.ReverseEngineerFiles)",
                  "spec.csharp": [
                    {
                      "uid": "System.Threading.Tasks.Task`1",
                      "name": "Task",
                      "fullName": "System.Threading.Tasks.Task",
                      "isExternal": true
                    },
                    {
                      "name": "<",
                      "fullName": "<",
                      "isExternal": false
                    },
                    {
                      "uid": "Microsoft.Data.Entity.Scaffolding.Internal.ReverseEngineerFiles",
                      "name": "ReverseEngineerFiles",
                      "fullName": "Microsoft.Data.Entity.Scaffolding.Internal.ReverseEngineerFiles",
                      "isExternal": false,
                      "href": "Microsoft.Data.Entity.Scaffolding.Internal.ReverseEngineerFiles.yml"
                    },
                    {
                      "name": ">",
                      "fullName": ">",
                      "isExternal": false
                    }
                  ],
                  "spec.vb": [
                    {
                      "uid": "System.Threading.Tasks.Task`1",
                      "name": "Task",
                      "fullName": "System.Threading.Tasks.Task",
                      "isExternal": true
                    },
                    {
                      "name": "(Of ",
                      "fullName": "(Of ",
                      "isExternal": false
                    },
                    {
                      "uid": "Microsoft.Data.Entity.Scaffolding.Internal.ReverseEngineerFiles",
                      "name": "ReverseEngineerFiles",
                      "fullName": "Microsoft.Data.Entity.Scaffolding.Internal.ReverseEngineerFiles",
                      "isExternal": false,
                      "href": "Microsoft.Data.Entity.Scaffolding.Internal.ReverseEngineerFiles.yml"
                    },
                    {
                      "name": ")",
                      "fullName": ")",
                      "isExternal": false
                    }
                  ],
                  "specName": "<xref href=\"System.Threading.Tasks.Task`1\" name=\"System.Threading.Tasks.Task\"/>&lt;<xref href=\"Microsoft.Data.Entity.Scaffolding.Internal.ReverseEngineerFiles\" name=\"Microsoft.Data.Entity.Scaffolding.Internal.ReverseEngineerFiles\"/>&gt;",
                  "id": "Task_ReverseEngineerFiles_",
                  "level": 0
                }
              }
            },
            "specName": "<xref href=\"Microsoft.Data.Entity.Design.DatabaseOperations.ReverseEngineerAsync(System.String,System.String,System.String,System.String,System.Collections.Generic.List{System.String},System.Collections.Generic.List{System.String},System.Boolean,System.Threading.CancellationToken)\" name=\"Microsoft.Data.Entity.Design.DatabaseOperations.ReverseEngineerAsync(System.String, System.String, System.String, System.String, System.Collections.Generic.List&lt;System.String&gt;, System.Collections.Generic.List&lt;System.String&gt;, System.Boolean, System.Threading.CancellationToken)\"/>",
            "level": 0,
            "docurl": "",
            "sourceurl": "https://github.com/chenkennt/EntityFramework/blob/dev/src/EntityFramework.Commands/Design/DatabaseOperations.cs/#L47"
          }
        ]
      }
    ],
    "href": "Microsoft.Data.Entity.Design.DatabaseOperations.yml",
    "name": "DatabaseOperations",
    "fullName": "Microsoft.Data.Entity.Design.DatabaseOperations",
    "type": "Class",
    "source": {
      "remote": {
        "path": "src/EntityFramework.Commands/Design/DatabaseOperations.cs",
        "branch": "dev",
        "repo": "https://github.com/chenkennt/EntityFramework.git"
      },
      "path": "src/EntityFramework.Commands/Design/DatabaseOperations.cs",
      "startLine": 17,
      "endLine": 0,
      "isExternal": false
    },
    "assemblies": [
      "EntityFramework.Commands"
    ],
    "namespace": "Microsoft.Data.Entity.Design",
    "syntax": {
      "content": "public class DatabaseOperations",
      "content.vb": "Public Class DatabaseOperations"
    },
    "inheritance": [
      {
        "uid": "System.Object",
        "parent": "System",
        "isExternal": true,
        "name": "Object",
        "fullName": "System.Object",
        "specName": "<xref href=\"System.Object\" name=\"System.Object\"/>",
        "id": "Object",
        "level": 0,
        "index": 0
      }
    ],
    "inheritedMembers": [
      "System.Object.ToString",
      "System.Object.Equals(System.Object)",
      "System.Object.Equals(System.Object,System.Object)",
      "System.Object.ReferenceEquals(System.Object,System.Object)",
      "System.Object.GetHashCode",
      "System.Object.GetType",
      "System.Object.MemberwiseClone"
    ],
    "specName": "<xref href=\"Microsoft.Data.Entity.Design.DatabaseOperations\" name=\"Microsoft.Data.Entity.Design.DatabaseOperations\"/>",
    "level": 1,
    "docurl": "",
    "sourceurl": "https://github.com/chenkennt/EntityFramework/blob/dev/src/EntityFramework.Commands/Design/DatabaseOperations.cs/#L18"
  },
  "isClass": true,
  "_allowToc": true
}
