
{
  "_lang": "csharp",
  "_tocPath": "reference/toc.html",
  "_navPath": "toc.html",
  "_rel": "../",
  "_navRel": "../toc.html",
  "_tocRel": "toc.html",
  "_appTitle": "Entity Framework",
  "item": {
    "uid": "Microsoft.Data.Entity.DbUpdateConcurrencyException",
    "id": "DbUpdateConcurrencyException",
    "parent": "Microsoft.Data.Entity",
    "children": [
      {
        "title": "Constructors",
        "id": "constructors",
        "children": [
          {
            "uid": "Microsoft.Data.Entity.DbUpdateConcurrencyException.#ctor(System.String,System.Collections.Generic.IReadOnlyList{Microsoft.Data.Entity.Update.IUpdateEntry})",
            "id": "DbUpdateConcurrencyException_String__IReadOnlyList_IUpdateEntry__",
            "parent": "Microsoft.Data.Entity.DbUpdateConcurrencyException",
            "href": "Microsoft.Data.Entity.DbUpdateConcurrencyException.yml",
            "name": "DbUpdateConcurrencyException(String, IReadOnlyList<IUpdateEntry>)",
            "name.vb": "DbUpdateConcurrencyException(String, IReadOnlyList(Of IUpdateEntry))",
            "fullName": "Microsoft.Data.Entity.DbUpdateConcurrencyException.DbUpdateConcurrencyException(System.String, System.Collections.Generic.IReadOnlyList<Microsoft.Data.Entity.Update.IUpdateEntry>)",
            "fullName.vb": "Microsoft.Data.Entity.DbUpdateConcurrencyException.DbUpdateConcurrencyException(System.String, System.Collections.Generic.IReadOnlyList(Of Microsoft.Data.Entity.Update.IUpdateEntry))",
            "type": "constructor",
            "source": {
              "remote": {
                "path": "src/EntityFramework.Core/DbUpdateConcurrencyException.cs",
                "branch": "dev",
                "repo": "https://github.com/chenkennt/EntityFramework.git"
              },
              "path": "src/EntityFramework.Core/DbUpdateConcurrencyException.cs",
              "startLine": 21,
              "endLine": 0,
              "isExternal": false
            },
            "assemblies": [
              "EntityFramework.Core"
            ],
            "namespace": "Microsoft.Data.Entity",
            "summary": "<p>Initializes a new instance of the <xref href=\"Microsoft.Data.Entity.DbUpdateConcurrencyException\"></xref> class.</p>\n",
            "syntax": {
              "content": "public DbUpdateConcurrencyException(string message, IReadOnlyList<IUpdateEntry> entries)",
              "content.vb": "Public Sub New(message As String, entries As IReadOnlyList(Of IUpdateEntry))",
              "parameters": [
                {
                  "id": "message",
                  "type": {
                    "uid": "System.String",
                    "parent": "System",
                    "isExternal": true,
                    "name": "String",
                    "fullName": "System.String",
                    "specName": "<xref href=\"System.String\" name=\"System.String\"/>",
                    "id": "String",
                    "level": 0
                  },
                  "description": "<p>The error message that explains the reason for the exception.</p>\n"
                },
                {
                  "id": "entries",
                  "type": {
                    "uid": "System.Collections.Generic.IReadOnlyList{Microsoft.Data.Entity.Update.IUpdateEntry}",
                    "parent": "System.Collections.Generic",
                    "definition": "System.Collections.Generic.IReadOnlyList`1",
                    "href": "Microsoft.Data.Entity.Update.IUpdateEntry.yml",
                    "name": "IReadOnlyList<IUpdateEntry>",
                    "name.vb": "IReadOnlyList(Of IUpdateEntry)",
                    "fullName": "System.Collections.Generic.IReadOnlyList<Microsoft.Data.Entity.Update.IUpdateEntry>",
                    "fullName.vb": "System.Collections.Generic.IReadOnlyList(Of Microsoft.Data.Entity.Update.IUpdateEntry)",
                    "spec.csharp": [
                      {
                        "uid": "System.Collections.Generic.IReadOnlyList`1",
                        "name": "IReadOnlyList",
                        "fullName": "System.Collections.Generic.IReadOnlyList",
                        "isExternal": true
                      },
                      {
                        "name": "<",
                        "fullName": "<",
                        "isExternal": false
                      },
                      {
                        "uid": "Microsoft.Data.Entity.Update.IUpdateEntry",
                        "name": "IUpdateEntry",
                        "fullName": "Microsoft.Data.Entity.Update.IUpdateEntry",
                        "isExternal": false,
                        "href": "Microsoft.Data.Entity.Update.IUpdateEntry.yml"
                      },
                      {
                        "name": ">",
                        "fullName": ">",
                        "isExternal": false
                      }
                    ],
                    "spec.vb": [
                      {
                        "uid": "System.Collections.Generic.IReadOnlyList`1",
                        "name": "IReadOnlyList",
                        "fullName": "System.Collections.Generic.IReadOnlyList",
                        "isExternal": true
                      },
                      {
                        "name": "(Of ",
                        "fullName": "(Of ",
                        "isExternal": false
                      },
                      {
                        "uid": "Microsoft.Data.Entity.Update.IUpdateEntry",
                        "name": "IUpdateEntry",
                        "fullName": "Microsoft.Data.Entity.Update.IUpdateEntry",
                        "isExternal": false,
                        "href": "Microsoft.Data.Entity.Update.IUpdateEntry.yml"
                      },
                      {
                        "name": ")",
                        "fullName": ")",
                        "isExternal": false
                      }
                    ],
                    "specName": "<xref href=\"System.Collections.Generic.IReadOnlyList`1\" name=\"System.Collections.Generic.IReadOnlyList\"/>&lt;<xref href=\"Microsoft.Data.Entity.Update.IUpdateEntry\" name=\"Microsoft.Data.Entity.Update.IUpdateEntry\"/>&gt;",
                    "id": "IReadOnlyList_IUpdateEntry_",
                    "level": 0
                  },
                  "description": "<p>The entries that were involved in the concurrency violation.</p>\n"
                }
              ]
            },
            "specName": "<xref href=\"Microsoft.Data.Entity.DbUpdateConcurrencyException.#ctor(System.String,System.Collections.Generic.IReadOnlyList{Microsoft.Data.Entity.Update.IUpdateEntry})\" name=\"Microsoft.Data.Entity.DbUpdateConcurrencyException.DbUpdateConcurrencyException(System.String, System.Collections.Generic.IReadOnlyList&lt;Microsoft.Data.Entity.Update.IUpdateEntry&gt;)\"/>",
            "level": 0,
            "docurl": "",
            "sourceurl": "https://github.com/chenkennt/EntityFramework/blob/dev/src/EntityFramework.Core/DbUpdateConcurrencyException.cs/#L22"
          }
        ]
      }
    ],
    "href": "Microsoft.Data.Entity.DbUpdateConcurrencyException.yml",
    "name": "DbUpdateConcurrencyException",
    "fullName": "Microsoft.Data.Entity.DbUpdateConcurrencyException",
    "type": "Class",
    "source": {
      "remote": {
        "path": "src/EntityFramework.Core/DbUpdateConcurrencyException.cs",
        "branch": "dev",
        "repo": "https://github.com/chenkennt/EntityFramework.git"
      },
      "path": "src/EntityFramework.Core/DbUpdateConcurrencyException.cs",
      "startLine": 14,
      "endLine": 0,
      "isExternal": false
    },
    "assemblies": [
      "EntityFramework.Core"
    ],
    "namespace": "Microsoft.Data.Entity",
    "summary": "<p>An exception that is thrown when a concurrency violation is encountered while saving to the database. A concurrency violation\noccurs when an unexpected number of rows are affected during save. This is usually because the data in the database has\nbeen modified since it was loaded into memory.</p>\n",
    "syntax": {
      "content": "public class DbUpdateConcurrencyException : DbUpdateException, ISerializable, _Exception",
      "content.vb": "Public Class DbUpdateConcurrencyException Inherits DbUpdateException Implements ISerializable, _Exception"
    },
    "inheritance": [
      {
        "uid": "System.Object",
        "parent": "System",
        "isExternal": true,
        "name": "Object",
        "fullName": "System.Object",
        "specName": "<xref href=\"System.Object\" name=\"System.Object\"/>",
        "id": "Object",
        "level": 0,
        "index": 0
      },
      {
        "uid": "System.Exception",
        "parent": "System",
        "isExternal": true,
        "name": "Exception",
        "fullName": "System.Exception",
        "specName": "<xref href=\"System.Exception\" name=\"System.Exception\"/>",
        "id": "Exception",
        "level": 0,
        "index": 1
      },
      {
        "uid": "Microsoft.Data.Entity.DbUpdateException",
        "parent": "Microsoft.Data.Entity",
        "isExternal": false,
        "href": "Microsoft.Data.Entity.DbUpdateException.yml",
        "name": "DbUpdateException",
        "fullName": "Microsoft.Data.Entity.DbUpdateException",
        "type": "class",
        "summary": "<p>An exception that is thrown when an error is encountered while saving to the database.</p>\n",
        "specName": "<xref href=\"Microsoft.Data.Entity.DbUpdateException\" name=\"Microsoft.Data.Entity.DbUpdateException\"/>",
        "id": "DbUpdateException",
        "level": 0,
        "index": 2
      }
    ],
    "implements": [
      "System.Runtime.Serialization.ISerializable",
      "System.Runtime.InteropServices._Exception"
    ],
    "inheritedMembers": [
      "Microsoft.Data.Entity.DbUpdateException.Entries",
      "System.Exception.GetBaseException",
      "System.Exception.ToString",
      "System.Exception.GetObjectData(System.Runtime.Serialization.SerializationInfo,System.Runtime.Serialization.StreamingContext)",
      "System.Exception.GetType",
      "System.Exception.Message",
      "System.Exception.Data",
      "System.Exception.InnerException",
      "System.Exception.TargetSite",
      "System.Exception.StackTrace",
      "System.Exception.HelpLink",
      "System.Exception.Source",
      "System.Exception.HResult",
      "System.Exception.SerializeObjectState",
      "System.Object.Equals(System.Object)",
      "System.Object.Equals(System.Object,System.Object)",
      "System.Object.ReferenceEquals(System.Object,System.Object)",
      "System.Object.GetHashCode",
      "System.Object.MemberwiseClone"
    ],
    "specName": "<xref href=\"Microsoft.Data.Entity.DbUpdateConcurrencyException\" name=\"Microsoft.Data.Entity.DbUpdateConcurrencyException\"/>",
    "level": 3,
    "docurl": "",
    "sourceurl": "https://github.com/chenkennt/EntityFramework/blob/dev/src/EntityFramework.Core/DbUpdateConcurrencyException.cs/#L15"
  },
  "isClass": true,
  "_allowToc": true
}
