
{
  "_lang": "csharp",
  "_tocPath": "reference/toc.html",
  "_navPath": "toc.html",
  "_rel": "../",
  "_navRel": "../toc.html",
  "_tocRel": "toc.html",
  "_appTitle": "Entity Framework",
  "item": {
    "uid": "Microsoft.Data.Entity.Scaffolding.Internal.Configuration.IndexConfiguration",
    "id": "IndexConfiguration",
    "parent": "Microsoft.Data.Entity.Scaffolding.Internal.Configuration",
    "children": [
      {
        "title": "Constructors",
        "id": "constructors",
        "children": [
          {
            "uid": "Microsoft.Data.Entity.Scaffolding.Internal.Configuration.IndexConfiguration.#ctor(System.String,Microsoft.Data.Entity.Metadata.Internal.Index)",
            "id": "IndexConfiguration_String__Index_",
            "parent": "Microsoft.Data.Entity.Scaffolding.Internal.Configuration.IndexConfiguration",
            "href": "Microsoft.Data.Entity.Scaffolding.Internal.Configuration.IndexConfiguration.yml",
            "name": "IndexConfiguration(String, Index)",
            "fullName": "Microsoft.Data.Entity.Scaffolding.Internal.Configuration.IndexConfiguration.IndexConfiguration(System.String, Microsoft.Data.Entity.Metadata.Internal.Index)",
            "type": "constructor",
            "source": {
              "remote": {
                "path": "src/EntityFramework.Commands/Scaffolding/Internal/Configuration/IndexConfiguration.cs",
                "branch": "dev",
                "repo": "https://github.com/chenkennt/EntityFramework.git"
              },
              "path": "src/EntityFramework.Commands/Scaffolding/Internal/Configuration/IndexConfiguration.cs",
              "startLine": 13,
              "endLine": 0,
              "isExternal": false
            },
            "assemblies": [
              "EntityFramework.Commands"
            ],
            "namespace": "Microsoft.Data.Entity.Scaffolding.Internal.Configuration",
            "syntax": {
              "content": "public IndexConfiguration(string lambdaIdentifier, Index index)",
              "content.vb": "Public Sub New(lambdaIdentifier As String, index As Index)",
              "parameters": [
                {
                  "id": "lambdaIdentifier",
                  "type": {
                    "uid": "System.String",
                    "parent": "System",
                    "isExternal": true,
                    "name": "String",
                    "fullName": "System.String",
                    "specName": "<xref href=\"System.String\" name=\"System.String\"/>",
                    "id": "String",
                    "level": 0
                  }
                },
                {
                  "id": "index",
                  "type": {
                    "uid": "Microsoft.Data.Entity.Metadata.Internal.Index",
                    "parent": "Microsoft.Data.Entity.Metadata.Internal",
                    "isExternal": false,
                    "href": "Microsoft.Data.Entity.Metadata.Internal.Index.yml",
                    "name": "Index",
                    "fullName": "Microsoft.Data.Entity.Metadata.Internal.Index",
                    "specName": "<xref href=\"Microsoft.Data.Entity.Metadata.Internal.Index\" name=\"Microsoft.Data.Entity.Metadata.Internal.Index\"/>",
                    "id": "Index",
                    "level": 0
                  }
                }
              ]
            },
            "specName": "<xref href=\"Microsoft.Data.Entity.Scaffolding.Internal.Configuration.IndexConfiguration.#ctor(System.String,Microsoft.Data.Entity.Metadata.Internal.Index)\" name=\"Microsoft.Data.Entity.Scaffolding.Internal.Configuration.IndexConfiguration.IndexConfiguration(System.String, Microsoft.Data.Entity.Metadata.Internal.Index)\"/>",
            "level": 0,
            "docurl": "",
            "sourceurl": "https://github.com/chenkennt/EntityFramework/blob/dev/src/EntityFramework.Commands/Scaffolding/Internal/Configuration/IndexConfiguration.cs/#L14"
          }
        ]
      },
      {
        "title": "Properties",
        "id": "properties",
        "children": [
          {
            "uid": "Microsoft.Data.Entity.Scaffolding.Internal.Configuration.IndexConfiguration.FluentApi",
            "id": "FluentApi",
            "parent": "Microsoft.Data.Entity.Scaffolding.Internal.Configuration.IndexConfiguration",
            "href": "Microsoft.Data.Entity.Scaffolding.Internal.Configuration.IndexConfiguration.yml",
            "name": "FluentApi",
            "fullName": "Microsoft.Data.Entity.Scaffolding.Internal.Configuration.IndexConfiguration.FluentApi",
            "type": "property",
            "source": {
              "remote": {
                "path": "src/EntityFramework.Commands/Scaffolding/Internal/Configuration/IndexConfiguration.cs",
                "branch": "dev",
                "repo": "https://github.com/chenkennt/EntityFramework.git"
              },
              "path": "src/EntityFramework.Commands/Scaffolding/Internal/Configuration/IndexConfiguration.cs",
              "startLine": 30,
              "endLine": 0,
              "isExternal": false
            },
            "assemblies": [
              "EntityFramework.Commands"
            ],
            "namespace": "Microsoft.Data.Entity.Scaffolding.Internal.Configuration",
            "syntax": {
                "content": "public virtual string FluentApi { get; }",
                "content.vb": "Public Overridable ReadOnly Property FluentApi As String",
                "parameters": [],
                "return": {
                  "type": {
                    "uid": "System.String",
                    "parent": "System",
                    "isExternal": true,
                    "name": "String",
                    "fullName": "System.String",
                    "specName": "<xref href=\"System.String\" name=\"System.String\"/>",
                    "id": "String",
                    "level": 0
                  }
                }
            },
            "specName": "<xref href=\"Microsoft.Data.Entity.Scaffolding.Internal.Configuration.IndexConfiguration.FluentApi\" name=\"Microsoft.Data.Entity.Scaffolding.Internal.Configuration.IndexConfiguration.FluentApi\"/>",
            "level": 0,
            "docurl": "",
            "sourceurl": "https://github.com/chenkennt/EntityFramework/blob/dev/src/EntityFramework.Commands/Scaffolding/Internal/Configuration/IndexConfiguration.cs/#L31"
          },
          {
            "uid": "Microsoft.Data.Entity.Scaffolding.Internal.Configuration.IndexConfiguration.For",
            "id": "For",
            "parent": "Microsoft.Data.Entity.Scaffolding.Internal.Configuration.IndexConfiguration",
            "href": "Microsoft.Data.Entity.Scaffolding.Internal.Configuration.IndexConfiguration.yml",
            "name": "For",
            "fullName": "Microsoft.Data.Entity.Scaffolding.Internal.Configuration.IndexConfiguration.For",
            "type": "property",
            "source": {
              "remote": {
                "path": "src/EntityFramework.Commands/Scaffolding/Internal/Configuration/IndexConfiguration.cs",
                "branch": "dev",
                "repo": "https://github.com/chenkennt/EntityFramework.git"
              },
              "path": "src/EntityFramework.Commands/Scaffolding/Internal/Configuration/IndexConfiguration.cs",
              "startLine": 28,
              "endLine": 0,
              "isExternal": false
            },
            "assemblies": [
              "EntityFramework.Commands"
            ],
            "namespace": "Microsoft.Data.Entity.Scaffolding.Internal.Configuration",
            "syntax": {
                "content": "public virtual string For { get; }",
                "content.vb": "Public Overridable ReadOnly Property For As String",
                "parameters": [],
                "return": {
                  "type": {
                    "uid": "System.String",
                    "parent": "System",
                    "isExternal": true,
                    "name": "String",
                    "fullName": "System.String",
                    "specName": "<xref href=\"System.String\" name=\"System.String\"/>",
                    "id": "String",
                    "level": 0
                  }
                }
            },
            "specName": "<xref href=\"Microsoft.Data.Entity.Scaffolding.Internal.Configuration.IndexConfiguration.For\" name=\"Microsoft.Data.Entity.Scaffolding.Internal.Configuration.IndexConfiguration.For\"/>",
            "level": 0,
            "docurl": "",
            "sourceurl": "https://github.com/chenkennt/EntityFramework/blob/dev/src/EntityFramework.Commands/Scaffolding/Internal/Configuration/IndexConfiguration.cs/#L29"
          },
          {
            "uid": "Microsoft.Data.Entity.Scaffolding.Internal.Configuration.IndexConfiguration.HasAttributeEquivalent",
            "id": "HasAttributeEquivalent",
            "parent": "Microsoft.Data.Entity.Scaffolding.Internal.Configuration.IndexConfiguration",
            "href": "Microsoft.Data.Entity.Scaffolding.Internal.Configuration.IndexConfiguration.yml",
            "name": "HasAttributeEquivalent",
            "fullName": "Microsoft.Data.Entity.Scaffolding.Internal.Configuration.IndexConfiguration.HasAttributeEquivalent",
            "type": "property",
            "source": {
              "remote": {
                "path": "src/EntityFramework.Commands/Scaffolding/Internal/Configuration/IndexConfiguration.cs",
                "branch": "dev",
                "repo": "https://github.com/chenkennt/EntityFramework.git"
              },
              "path": "src/EntityFramework.Commands/Scaffolding/Internal/Configuration/IndexConfiguration.cs",
              "startLine": 27,
              "endLine": 0,
              "isExternal": false
            },
            "assemblies": [
              "EntityFramework.Commands"
            ],
            "namespace": "Microsoft.Data.Entity.Scaffolding.Internal.Configuration",
            "syntax": {
                "content": "public virtual bool HasAttributeEquivalent { get; }",
                "content.vb": "Public Overridable ReadOnly Property HasAttributeEquivalent As Boolean",
                "parameters": [],
                "return": {
                  "type": {
                    "uid": "System.Boolean",
                    "parent": "System",
                    "isExternal": true,
                    "name": "Boolean",
                    "fullName": "System.Boolean",
                    "specName": "<xref href=\"System.Boolean\" name=\"System.Boolean\"/>",
                    "id": "Boolean",
                    "level": 0
                  }
                }
            },
            "specName": "<xref href=\"Microsoft.Data.Entity.Scaffolding.Internal.Configuration.IndexConfiguration.HasAttributeEquivalent\" name=\"Microsoft.Data.Entity.Scaffolding.Internal.Configuration.IndexConfiguration.HasAttributeEquivalent\"/>",
            "level": 0,
            "docurl": "",
            "sourceurl": "https://github.com/chenkennt/EntityFramework/blob/dev/src/EntityFramework.Commands/Scaffolding/Internal/Configuration/IndexConfiguration.cs/#L28"
          },
          {
            "uid": "Microsoft.Data.Entity.Scaffolding.Internal.Configuration.IndexConfiguration.Index",
            "id": "Index",
            "parent": "Microsoft.Data.Entity.Scaffolding.Internal.Configuration.IndexConfiguration",
            "href": "Microsoft.Data.Entity.Scaffolding.Internal.Configuration.IndexConfiguration.yml",
            "name": "Index",
            "fullName": "Microsoft.Data.Entity.Scaffolding.Internal.Configuration.IndexConfiguration.Index",
            "type": "property",
            "source": {
              "remote": {
                "path": "src/EntityFramework.Commands/Scaffolding/Internal/Configuration/IndexConfiguration.cs",
                "branch": "dev",
                "repo": "https://github.com/chenkennt/EntityFramework.git"
              },
              "path": "src/EntityFramework.Commands/Scaffolding/Internal/Configuration/IndexConfiguration.cs",
              "startLine": 25,
              "endLine": 0,
              "isExternal": false
            },
            "assemblies": [
              "EntityFramework.Commands"
            ],
            "namespace": "Microsoft.Data.Entity.Scaffolding.Internal.Configuration",
            "syntax": {
                "content": "public virtual Index Index { get; }",
                "content.vb": "Public Overridable ReadOnly Property Index As Index",
                "parameters": [],
                "return": {
                  "type": {
                    "uid": "Microsoft.Data.Entity.Metadata.Internal.Index",
                    "parent": "Microsoft.Data.Entity.Metadata.Internal",
                    "isExternal": false,
                    "href": "Microsoft.Data.Entity.Metadata.Internal.Index.yml",
                    "name": "Index",
                    "fullName": "Microsoft.Data.Entity.Metadata.Internal.Index",
                    "specName": "<xref href=\"Microsoft.Data.Entity.Metadata.Internal.Index\" name=\"Microsoft.Data.Entity.Metadata.Internal.Index\"/>",
                    "id": "Index",
                    "level": 0
                  }
                }
            },
            "specName": "<xref href=\"Microsoft.Data.Entity.Scaffolding.Internal.Configuration.IndexConfiguration.Index\" name=\"Microsoft.Data.Entity.Scaffolding.Internal.Configuration.IndexConfiguration.Index\"/>",
            "level": 0,
            "docurl": "",
            "sourceurl": "https://github.com/chenkennt/EntityFramework/blob/dev/src/EntityFramework.Commands/Scaffolding/Internal/Configuration/IndexConfiguration.cs/#L26"
          },
          {
            "uid": "Microsoft.Data.Entity.Scaffolding.Internal.Configuration.IndexConfiguration.LambdaIdentifier",
            "id": "LambdaIdentifier",
            "parent": "Microsoft.Data.Entity.Scaffolding.Internal.Configuration.IndexConfiguration",
            "href": "Microsoft.Data.Entity.Scaffolding.Internal.Configuration.IndexConfiguration.yml",
            "name": "LambdaIdentifier",
            "fullName": "Microsoft.Data.Entity.Scaffolding.Internal.Configuration.IndexConfiguration.LambdaIdentifier",
            "type": "property",
            "source": {
              "remote": {
                "path": "src/EntityFramework.Commands/Scaffolding/Internal/Configuration/IndexConfiguration.cs",
                "branch": "dev",
                "repo": "https://github.com/chenkennt/EntityFramework.git"
              },
              "path": "src/EntityFramework.Commands/Scaffolding/Internal/Configuration/IndexConfiguration.cs",
              "startLine": 24,
              "endLine": 0,
              "isExternal": false
            },
            "assemblies": [
              "EntityFramework.Commands"
            ],
            "namespace": "Microsoft.Data.Entity.Scaffolding.Internal.Configuration",
            "syntax": {
                "content": "public virtual string LambdaIdentifier { get; }",
                "content.vb": "Public Overridable ReadOnly Property LambdaIdentifier As String",
                "parameters": [],
                "return": {
                  "type": {
                    "uid": "System.String",
                    "parent": "System",
                    "isExternal": true,
                    "name": "String",
                    "fullName": "System.String",
                    "specName": "<xref href=\"System.String\" name=\"System.String\"/>",
                    "id": "String",
                    "level": 0
                  }
                }
            },
            "specName": "<xref href=\"Microsoft.Data.Entity.Scaffolding.Internal.Configuration.IndexConfiguration.LambdaIdentifier\" name=\"Microsoft.Data.Entity.Scaffolding.Internal.Configuration.IndexConfiguration.LambdaIdentifier\"/>",
            "level": 0,
            "docurl": "",
            "sourceurl": "https://github.com/chenkennt/EntityFramework/blob/dev/src/EntityFramework.Commands/Scaffolding/Internal/Configuration/IndexConfiguration.cs/#L25"
          }
        ]
      }
    ],
    "href": "Microsoft.Data.Entity.Scaffolding.Internal.Configuration.IndexConfiguration.yml",
    "name": "IndexConfiguration",
    "fullName": "Microsoft.Data.Entity.Scaffolding.Internal.Configuration.IndexConfiguration",
    "type": "Class",
    "source": {
      "remote": {
        "path": "src/EntityFramework.Commands/Scaffolding/Internal/Configuration/IndexConfiguration.cs",
        "branch": "dev",
        "repo": "https://github.com/chenkennt/EntityFramework.git"
      },
      "path": "src/EntityFramework.Commands/Scaffolding/Internal/Configuration/IndexConfiguration.cs",
      "startLine": 11,
      "endLine": 0,
      "isExternal": false
    },
    "assemblies": [
      "EntityFramework.Commands"
    ],
    "namespace": "Microsoft.Data.Entity.Scaffolding.Internal.Configuration",
    "syntax": {
      "content": "public class IndexConfiguration : IFluentApiConfiguration",
      "content.vb": "Public Class IndexConfiguration Implements IFluentApiConfiguration"
    },
    "inheritance": [
      {
        "uid": "System.Object",
        "parent": "System",
        "isExternal": true,
        "name": "Object",
        "fullName": "System.Object",
        "specName": "<xref href=\"System.Object\" name=\"System.Object\"/>",
        "id": "Object",
        "level": 0,
        "index": 0
      }
    ],
    "implements": [
      "Microsoft.Data.Entity.Scaffolding.Internal.Configuration.IFluentApiConfiguration"
    ],
    "inheritedMembers": [
      "System.Object.ToString",
      "System.Object.Equals(System.Object)",
      "System.Object.Equals(System.Object,System.Object)",
      "System.Object.ReferenceEquals(System.Object,System.Object)",
      "System.Object.GetHashCode",
      "System.Object.GetType",
      "System.Object.MemberwiseClone"
    ],
    "specName": "<xref href=\"Microsoft.Data.Entity.Scaffolding.Internal.Configuration.IndexConfiguration\" name=\"Microsoft.Data.Entity.Scaffolding.Internal.Configuration.IndexConfiguration\"/>",
    "level": 1,
    "docurl": "",
    "sourceurl": "https://github.com/chenkennt/EntityFramework/blob/dev/src/EntityFramework.Commands/Scaffolding/Internal/Configuration/IndexConfiguration.cs/#L12"
  },
  "isClass": true,
  "_allowToc": true
}
